odoo8_addon_crm_lead_invoice_address-8.0.1.0.0.99.dev36-py3.8-nspkg.pth
odoo_addons/crm_lead_invoice_address/README.rst
odoo_addons/crm_lead_invoice_address/__init__.py
odoo_addons/crm_lead_invoice_address/__openerp__.py
odoo_addons/crm_lead_invoice_address/exceptions.py
odoo_addons/crm_lead_invoice_address/i18n/bg.po
odoo_addons/crm_lead_invoice_address/i18n/ca.po
odoo_addons/crm_lead_invoice_address/i18n/crm_lead_invoice_address.pot
odoo_addons/crm_lead_invoice_address/i18n/cs.po
odoo_addons/crm_lead_invoice_address/i18n/da.po
odoo_addons/crm_lead_invoice_address/i18n/de.po
odoo_addons/crm_lead_invoice_address/i18n/el_GR.po
odoo_addons/crm_lead_invoice_address/i18n/es.po
odoo_addons/crm_lead_invoice_address/i18n/es_ES.po
odoo_addons/crm_lead_invoice_address/i18n/es_MX.po
odoo_addons/crm_lead_invoice_address/i18n/es_VE.po
odoo_addons/crm_lead_invoice_address/i18n/eu.po
odoo_addons/crm_lead_invoice_address/i18n/fi.po
odoo_addons/crm_lead_invoice_address/i18n/fr.po
odoo_addons/crm_lead_invoice_address/i18n/fr_CH.po
odoo_addons/crm_lead_invoice_address/i18n/gl.po
odoo_addons/crm_lead_invoice_address/i18n/hr.po
odoo_addons/crm_lead_invoice_address/i18n/hr_HR.po
odoo_addons/crm_lead_invoice_address/i18n/hu.po
odoo_addons/crm_lead_invoice_address/i18n/id.po
odoo_addons/crm_lead_invoice_address/i18n/it.po
odoo_addons/crm_lead_invoice_address/i18n/nb.po
odoo_addons/crm_lead_invoice_address/i18n/nb_NO.po
odoo_addons/crm_lead_invoice_address/i18n/nl.po
odoo_addons/crm_lead_invoice_address/i18n/nl_NL.po
odoo_addons/crm_lead_invoice_address/i18n/pl.po
odoo_addons/crm_lead_invoice_address/i18n/pt.po
odoo_addons/crm_lead_invoice_address/i18n/pt_BR.po
odoo_addons/crm_lead_invoice_address/i18n/pt_PT.po
odoo_addons/crm_lead_invoice_address/i18n/ro.po
odoo_addons/crm_lead_invoice_address/i18n/ru.po
odoo_addons/crm_lead_invoice_address/i18n/sk.po
odoo_addons/crm_lead_invoice_address/i18n/sl.po
odoo_addons/crm_lead_invoice_address/i18n/sv.po
odoo8_addon_crm_lead_invoice_address-8.0.1.0.0.99.dev36.dist-info/METADATA
odoo8_addon_crm_lead_invoice_address-8.0.1.0.0.99.dev36.dist-info/WHEEL
odoo8_addon_crm_lead_invoice_address-8.0.1.0.0.99.dev36.dist-info/namespace_packages.txt
odoo8_addon_crm_lead_invoice_address-8.0.1.0.0.99.dev36.dist-info/top_level.txt
odoo8_addon_crm_lead_invoice_address-8.0.1.0.0.99.dev36.dist-info/RECORD
